[
  {
    "name": "Bc. Peter Kovács",
    "companyName": "Bc. Peter Kovács",
    "cin": "43615864",
    "businessAddress": ", 94638 Virt 5"
  },
  {
    "name": "Bc. Peter Kovács",
    "companyName": "Bc. Peter Kovács - AZ media",
    "cin": "35202084",
    "businessAddress": "J.Fučíka 19, 94101 Bánov"
  },
  {
    "name": "Bc. Peter Kováč",
    "companyName": "Bc. Peter Kováč",
    "cin": "50033115",
    "businessAddress": "Puškinova 1167/35, 09101 Stropkov"
  },
  {
    "name": "Bc. Peter Kováč",
    "companyName": "Bc. Peter Kováč",
    "cin": "52032221",
    "businessAddress": "Partizánska 438/65, 94911 Nitra"
  },
  {
    "name": "Bc. Peter Kováč",
    "companyName": "Bc. Peter Kováč",
    "cin": "47923199",
    "businessAddress": "Jahodová ulica 3198/9, 90028 Ivanka pri Dunaji"
  },
  {
    "name": "Bc. Peter Kováč  OK",
    "companyName": "Bc. Peter Kováč  OK - CONSULT",
    "cin": "44866135",
    "businessAddress": "Rožňavská 847/1, 97901 Rimavská Sobota"
  },
  {
    "name": "Bc. Peter Kovačik",
    "companyName": "Bc. Peter Kovačik",
    "cin": "46625445",
    "businessAddress": ", 04445 Vyšná Kamenica 89"
  },
  {
    "name": "Dr. Peter Kováč",
    "companyName": "Dr. Peter Kováč - B M S",
    "cin": "36980927",
    "businessAddress": "Súmračná 16, 82101 Bratislava-Ružinov"
  },
  {
    "name": "Ing. Peter Kovács",
    "companyName": "Ing. Peter Kovács",
    "cin": "44059574",
    "businessAddress": "Ku Bratke 2914/38, 93405 Levice"
  },
  {
    "name": "Ing. Peter Kovács",
    "companyName": "Ing. Peter Kovács",
    "cin": "35369817",
    "businessAddress": "Záhradnícka 6237/37, 92901 Dunajská Streda"
  },
  {
    "name": "Ing. Peter Kovács",
    "companyName": "Ing. Peter Kovács",
    "cin": "37425048",
    "businessAddress": "Mochovská 22, 93401 Levice"
  },
  {
    "name": "Ing. Peter Kovács",
    "companyName": "Ing. Peter Kovács",
    "cin": "50138774",
    "businessAddress": ", 98001 Rimavské Janovce 246"
  },
  {
    "name": "Ing. Peter Kovács",
    "companyName": "Ing. Peter Kovács",
    "cin": "51444275",
    "businessAddress": ", 92501 Matúškovo 933"
  },
  {
    "name": "Ing. Peter Kovács",
    "companyName": "Ing. Peter Kovács - BAU KOL",
    "cin": "41613139",
    "businessAddress": "Palatínova 59/10, 94501 Komárno"
  },
  {
    "name": "Ing. Peter Kováč",
    "companyName": "Ing. Peter Kováč",
    "cin": "41409256",
    "businessAddress": "Závodie, Pod sadom 701/3, 01004 Žilina"
  },
  {
    "name": "Ing. Peter Kováč",
    "companyName": "Ing. Peter Kováč",
    "cin": "17956277",
    "businessAddress": "Dolná 19, 97401 Banská Bystrica"
  },
  {
    "name": "Ing. Peter Kováč",
    "companyName": "Ing. Peter Kováč",
    "cin": "31057951",
    "businessAddress": "Štefánika 2556, 02201 Čadca"
  },
  {
    "name": "Ing. Peter Kováč",
    "companyName": "Ing. Peter Kováč",
    "cin": "40989330",
    "businessAddress": "J.Petrikovicha 4405/3, 03601 Martin"
  },
  {
    "name": "Ing. Peter Kováč",
    "companyName": "Ing. Peter Kováč",
    "cin": "53443357",
    "businessAddress": ", 94147 Radava 354"
  },
  {
    "name": "Ing. Peter Kováč",
    "companyName": "Ing. Peter Kováč",
    "cin": "54803853",
    "businessAddress": "Ul. ku Bratke 2911/26, 93405 Levice"
  }
]